{"name":"test004","id":"com.bestbuy.bestbuyinfo.CategoriesCRUDTestWithSteps:test004","testCaseName":"com.bestbuy.bestbuyinfo.CategoriesCRUDTestWithSteps","testSteps":[{"number":1,"description":"Deleting Category information with CategoryID: abcat0101001","duration":143,"startTime":"2022-01-10T16:18:25.471Z[Europe/London]","result":"SUCCESS","precondition":false,"children":[{"number":2,"description":"DELETE http://localhost:3030/categories/abcat0101001\r\r","duration":1,"startTime":"2022-01-10T16:18:25.613Z[Europe/London]","result":"SUCCESS","restQuery":{"method":"DELETE","path":"http://localhost:3030/categories/abcat0101001\r\r","content":"\r","contentType":"null","requestHeaders":"Accept\u003d*/*\r\r","requestCookies":"\r\r","responseHeaders":"X-Powered-By: Express\nAccess-Control-Allow-Origin: *\nAllow: GET,POST,PUT,PATCH,DELETE\nVary: Accept, Accept-Encoding\nContent-Type: application/json; charset\u003dutf-8\nContent-Length: 147\nETag: W/\"93-g28v7cPkMvbEf0KFlDJqAG9f1Pk\"\nDate: Mon, 10 Jan 2022 16:18:25 GMT\nConnection: keep-alive\r","responseCookies":"\r","responseBody":"{\n    \"id\": \"abcat0101001\",\n    \"name\": \"Electronics \u0026 Computers93042 (Updated)\",\n    \"createdAt\": \"2016-11-17T17:57:04.285Z\",\n    \"updatedAt\": \"2022-01-10T16:18:25.347Z\"\n}","statusCode":200},"precondition":false}]},{"number":3,"description":"Getting Category information with CategoryID: abcat0101001","duration":26,"startTime":"2022-01-10T16:18:25.615Z[Europe/London]","result":"SUCCESS","precondition":false,"children":[{"number":4,"description":"GET http://localhost:3030/categories/abcat0101001\r\r","duration":0,"startTime":"2022-01-10T16:18:25.641Z[Europe/London]","result":"SUCCESS","restQuery":{"method":"GET","path":"http://localhost:3030/categories/abcat0101001\r\r","content":"\r","contentType":"null","requestHeaders":"Accept\u003d*/*\r\r","requestCookies":"\r\r","responseHeaders":"X-Powered-By: Express\nAccess-Control-Allow-Origin: *\nAllow: GET,POST,PUT,PATCH,DELETE\nContent-Type: application/json; charset\u003dutf-8\nContent-Length: 116\nETag: W/\"74-BakoYwLvJkOiCi6saCbrSVMJeP4\"\nVary: Accept-Encoding\nDate: Mon, 10 Jan 2022 16:18:25 GMT\nConnection: keep-alive\r","responseCookies":"\r","responseBody":"{\n    \"name\": \"NotFound\",\n    \"message\": \"No record found for id \u0027abcat0101001\u0027\",\n    \"code\": 404,\n    \"className\": \"not-found\",\n    \"errors\": {\n        \n    }\n}","statusCode":404},"precondition":false}]}],"userStory":{"id":"com.bestbuy.bestbuyinfo.CategoriesCRUDTestWithSteps","storyName":"Categories CRUD test with steps","storyClassName":"com.bestbuy.bestbuyinfo.CategoriesCRUDTestWithSteps","path":"com.bestbuy.bestbuyinfo","type":"story"},"featureTag":{"name":"Bestbuyinfo/Categories CRUD test with steps","type":"story"},"title":"Delete Category and verify if the Category is deleted","tags":[{"name":"Bestbuyinfo/Categories CRUD test with steps","type":"story"}],"startTime":"2022-01-10T16:18:25.470Z[Europe/London]","duration":172,"projectKey":"","manual":false,"testSource":"JUnit","result":"SUCCESS"}